<?xml version="1.0" encoding="utf-8"?>
<LanguageManager>
    <Translations>
    
        <Translation Key="ViscosimeterSettings">
            <English>Viscosimeter Settings</English>
            <German>Viscosimeter Einstellungen</German>
        </Translation>

        <Translation Key="FluidType">
            <English>Fluid Type:</English>
            <German>Flüssigkeit:</German>
        </Translation>

        <Translation Key="FluidTemp">
            <English>Fluid Temp C°</English>
            <German>Flüssigkeit Temp C°</German>
        </Translation>

        <Translation Key="MeasureLength">
            <English>Measure Length</English>
            <German>Länge messen</German>
        </Translation>


        <Translation Key="ResetBall">
            <English>Reset Ball</English>
            <German>Kugel zurücksetzen</German>
        </Translation>

        <Translation Key="StopWatch">
            <English>Stopwatch</English>
            <German>Stoppuhr</German>
        </Translation>

        <Translation Key="StopWatchHover">
            <English>Move your cursor over the 'Start' button to start the drop countdown.</English>
            <German>Halte den Mauszeiger über dem 'Start' Knopf um den Countdown für den Fall zu starten.</German>
        </Translation>


        <Translation Key="BallCamera">
            <English>Ball Camera</English>
            <German>Kugel Kamera</German>
        </Translation>

        <Translation Key="Reset">
            <English>Reset</English>
            <German>Zurücksetzen</German>
        </Translation>


        <Translation Key="StartSlomo">
            <English>Start Slow Motion</English>
            <German>Zeitlupe starten</German>
        </Translation>

        <Translation Key="StopSlomo">
            <English>Stop Slow Motion</English>
            <German>Zeitlupe stoppen</German>
        </Translation>

        <Translation Key="TooltipPycnometer">
            <English>~Pycnometer\n'Used to measure the density of liquids by weighing on a @scale'. Fill it using the white @faucet' on the @tube'.</English>
            <German>~Pycnometer\n'Wird benutzt um die Dichte von Flüssigkeiten zu messen indem man sie gefüllt auf eine @Waage' stellt'. Fülle es mit dem weißen @Hahn' auf dem @Fallrohr'.</German>
        </Translation>

        <Translation Key="TooltipBall">
            <English>~Ball\n'A ball made of metal.</English>
            <German>~Kugel\n'Eine Kugel aus Metall.</German>
        </Translation>
        
        <Translation Key="TooltipFaucet">
            <English>~Faucet\n'Move the @pycnometer' under the faucet and click the faucet, to fill and empty the @pycnometer'.</English>
            <German>~Hahn\n'Bewege das @Pycnometer' unter den Hahn und klicke auf den Hahn, um das @Pycnometer' zu füllen und zu entleeren.</German>
        </Translation>

        <Translation Key="TooltipTube">
            <English>~Tube\n'This tube is filled with a liquid chosen in the menu to the left. The liquid will slow the @ball' down as it falls through it.</English>
            <German>~Fallrohr\n'Dieses Fallrohr wird mit der links im Menü ausgewählten Flüssigkeit gefüllt. Die Flüssigkeit bremst den Fall der @Kugel'.</German>
        </Translation>
        
    </Translations>
</LanguageManager>
